.gitignore
.pylintrc
.travis.yml
MANIFEST.in
Makefile
distmqtt.cfg.sample
distmqtt.service
license.txt
mq
readme.rst
setup.cfg
setup.py
tox.ini
distmqtt/__init__.py
distmqtt/adapters.py
distmqtt/broker.py
distmqtt/client.py
distmqtt/codecs.py
distmqtt/distkv_broker.py
distmqtt/errors.py
distmqtt/session.py
distmqtt/test.py
distmqtt/utils.py
distmqtt/version.py
distmqtt.egg-info/PKG-INFO
distmqtt.egg-info/SOURCES.txt
distmqtt.egg-info/dependency_links.txt
distmqtt.egg-info/entry_points.txt
distmqtt.egg-info/requires.txt
distmqtt.egg-info/top_level.txt
distmqtt/mqtt/__init__.py
distmqtt/mqtt/connack.py
distmqtt/mqtt/connect.py
distmqtt/mqtt/constants.py
distmqtt/mqtt/disconnect.py
distmqtt/mqtt/packet.py
distmqtt/mqtt/pingreq.py
distmqtt/mqtt/pingresp.py
distmqtt/mqtt/puback.py
distmqtt/mqtt/pubcomp.py
distmqtt/mqtt/publish.py
distmqtt/mqtt/pubrec.py
distmqtt/mqtt/pubrel.py
distmqtt/mqtt/suback.py
distmqtt/mqtt/subscribe.py
distmqtt/mqtt/unsuback.py
distmqtt/mqtt/unsubscribe.py
distmqtt/mqtt/protocol/__init__.py
distmqtt/mqtt/protocol/broker_handler.py
distmqtt/mqtt/protocol/client_handler.py
distmqtt/mqtt/protocol/handler.py
distmqtt/plugins/__init__.py
distmqtt/plugins/authentication.py
distmqtt/plugins/logging.py
distmqtt/plugins/manager.py
distmqtt/plugins/persistence.py
distmqtt/plugins/topic_checking.py
distmqtt/plugins/sys/__init__.py
distmqtt/plugins/sys/broker.py
distmqtt/scripts/__init__.py
distmqtt/scripts/broker_script.py
distmqtt/scripts/default_broker.yaml
distmqtt/scripts/default_client.yaml
distmqtt/scripts/pub_script.py
distmqtt/scripts/sub_script.py
docs/Makefile
docs/changelog.rst
docs/conf.py
docs/index.rst
docs/license.rst
docs/quickstart.rst
docs/_static/theme_overrides.css
docs/_templates/layout.html
docs/references/broker.rst
docs/references/common.rst
docs/references/distmqtt.rst
docs/references/distmqtt_pub.rst
docs/references/distmqtt_sub.rst
docs/references/index.rst
docs/references/mqttclient.rst
samples/broker_acl.py
samples/broker_start.py
samples/broker_taboo.py
samples/client_keepalive.py
samples/client_publish.py
samples/client_publish_acl.py
samples/client_publish_ssl.py
samples/client_publish_ws.py
