Metadata-Version: 2.1
Name: distmqtt
Version: 0.33.1
Summary: MQTT client/broker using anyio and distkv
Home-page: https://github.com/smurfix/distmqtt
Author: Matthias Urlichs
Author-email: matthias@urlichs.de
License: MIT
Platform: all
Classifier: Development Status :: 4 - Beta
Classifier: Intended Audience :: Developers
Classifier: License :: OSI Approved :: MIT License
Classifier: Operating System :: POSIX
Classifier: Operating System :: MacOS
Classifier: Operating System :: Microsoft :: Windows
Classifier: Programming Language :: Python :: 3.6
Classifier: Programming Language :: Python :: 3.7
Classifier: Programming Language :: Python :: 3.8
Classifier: Topic :: Communications
Classifier: Topic :: Internet
Requires-Python: >=3.6
Provides-Extra: distkv
